setup.py
autobahn/__init__.py
autobahn/_version.py
autobahn/flashpolicy.py
autobahn/httpstatus.py
autobahn/pbkdf2.py
autobahn/prefixmap.py
autobahn/resource.py
autobahn/useragent.py
autobahn/util.py
autobahn/wamp.py
autobahn/websocket.py
autobahn_rce.egg-info/PKG-INFO
autobahn_rce.egg-info/SOURCES.txt
autobahn_rce.egg-info/dependency_links.txt
autobahn_rce.egg-info/not-zip-safe
autobahn_rce.egg-info/requires.txt
autobahn_rce.egg-info/top_level.txt
src/utf8validator.c
src/xormasker.c