Metadata-Version: 1.1
Name: autobahn-rce
Version: 0.6.0.4
Summary: AutobahnPython - Optimised and modified for the RoboEarth Cloud Engine.
Home-page: https://github.com/IDSCETHZurich/autobahn_rce
Author: Dhananjay Sathe
Author-email: dhananjaysathe@gmail.com
License: Apache License 2.0
Keywords: autobahn robotics cloud roboearth rapyuta autobahn.ws websocket realtime rfc6455 wamp rpc pubsub
Platform: Any
Classifier: License :: OSI Approved :: Apache Software License
Classifier: Development Status :: 5 - Production/Stable
Classifier: Environment :: Console
Classifier: Framework :: Twisted
Classifier: Intended Audience :: Developers
Classifier: Operating System :: OS Independent
Classifier: Programming Language :: Python
Classifier: Topic :: Internet
Classifier: Topic :: Software Development :: Libraries
